{"actions": 651, "added_lines": 53377.0, "added_lines_30": 173406, "added_lines_365": 11373113, "added_lines_7": 29100, "authors": 20, "authors_30": 0, "authors_365": 0, "authors_7": 0, "avg_commits_author": 14.5, "avg_commits_week": 1.05, "avg_files_author": 20.95, "avg_files_week": 1.52, "branches": 1, "commits": 290, "commits_30": 0, "commits_365": 0, "commits_7": 0, "committers": 20, "diff_netadded_lines_30": -1311875, "diff_netadded_lines_365": 4241531, "diff_netadded_lines_7": 12223, "diff_netauthors_30": 0, "diff_netauthors_365": 0, "diff_netauthors_7": 0, "diff_netcommits_30": 0, "diff_netcommits_365": 0, "diff_netcommits_7": 0, "diff_netfiles_30": 0, "diff_netfiles_365": 0, "diff_netfiles_7": 0, "diff_netnewauthors_30": 0, "diff_netnewauthors_365": 0, "diff_netnewauthors_7": 0, "diff_netremoved_lines_30": -986759, "diff_netremoved_lines_365": 7448514, "diff_netremoved_lines_7": 38977, "files": 419, "files_30": 0, "files_365": 0, "files_7": 0, "first_date": "2004-01-01", "last_date": "2015-04-13", "newauthors": 10, "newauthors_30": 0, "newauthors_365": 0, "newauthors_7": 0, "percentage_added_lines_30": 88, "percentage_added_lines_365": 59, "percentage_added_lines_7": 72, "percentage_authors_30": 0, "percentage_authors_365": 0, "percentage_authors_7": 0, "percentage_commits_30": 0, "percentage_commits_365": 0, "percentage_commits_7": 0, "percentage_files_30": 0, "percentage_files_365": 0, "percentage_files_7": 0, "percentage_newauthors_30": 0, "percentage_newauthors_365": 0, "percentage_newauthors_7": 0, "percentage_removed_lines_30": 71, "percentage_removed_lines_365": 353, "percentage_removed_lines_7": 267, "removed_lines": 2128.0, "removed_lines_30": 388481, "removed_lines_365": 9555345, "removed_lines_7": 53563, "repositories": 1}